{"config":{"output_file":null,"full_docs":false,"pub_only":false,"reachable_only":false,"distro_crate":false,"signatures":false,"borrow_data":false},"version":"0.19.1","compilation":{"directory":"c:\\Users\\Raimi\\Documents\\RustProjects\\rust-practice\\rust\\health-statistics","program":"C:\\Users\\Raimi\\.rustup\\toolchains\\stable-x86_64-pc-windows-msvc\\bin\\rls.exe","arguments":[],"output":"c:\\Users\\Raimi\\Documents\\RustProjects\\rust-practice\\rust\\health-statistics\\target\\rls\\debug\\deps\\libhealth_statistics-29b037eadc298a03.rmeta"},"prelude":{"crate_id":{"name":"health_statistics","disambiguator":[676427346782488213,17376296890811155149]},"crate_root":"tests","external_crates":[{"file_name":"c:\\Users\\Raimi\\Documents\\RustProjects\\rust-practice\\rust\\health-statistics\\tests\\health-statistics.rs","num":1,"id":{"name":"std","disambiguator":[902711862199739234,15082167224296373374]}},{"file_name":"c:\\Users\\Raimi\\Documents\\RustProjects\\rust-practice\\rust\\health-statistics\\tests\\health-statistics.rs","num":2,"id":{"name":"core","disambiguator":[5048311760381386034,12753961808535803278]}},{"file_name":"c:\\Users\\Raimi\\Documents\\RustProjects\\rust-practice\\rust\\health-statistics\\tests\\health-statistics.rs","num":3,"id":{"name":"compiler_builtins","disambiguator":[847775214756591688,12437863933651081164]}},{"file_name":"c:\\Users\\Raimi\\Documents\\RustProjects\\rust-practice\\rust\\health-statistics\\tests\\health-statistics.rs","num":4,"id":{"name":"rustc_std_workspace_core","disambiguator":[18098153966720408130,4102567439342721650]}},{"file_name":"c:\\Users\\Raimi\\Documents\\RustProjects\\rust-practice\\rust\\health-statistics\\tests\\health-statistics.rs","num":5,"id":{"name":"alloc","disambiguator":[14085577876822856882,15393158987199036233]}},{"file_name":"c:\\Users\\Raimi\\Documents\\RustProjects\\rust-practice\\rust\\health-statistics\\tests\\health-statistics.rs","num":6,"id":{"name":"libc","disambiguator":[3188366355873518403,14471389999965490426]}},{"file_name":"c:\\Users\\Raimi\\Documents\\RustProjects\\rust-practice\\rust\\health-statistics\\tests\\health-statistics.rs","num":7,"id":{"name":"unwind","disambiguator":[10237517513868340142,18396708545822173986]}},{"file_name":"c:\\Users\\Raimi\\Documents\\RustProjects\\rust-practice\\rust\\health-statistics\\tests\\health-statistics.rs","num":8,"id":{"name":"cfg_if","disambiguator":[17305999185247584930,14125623615750666193]}},{"file_name":"c:\\Users\\Raimi\\Documents\\RustProjects\\rust-practice\\rust\\health-statistics\\tests\\health-statistics.rs","num":9,"id":{"name":"hashbrown","disambiguator":[7451980452763147359,4800032867518142595]}},{"file_name":"c:\\Users\\Raimi\\Documents\\RustProjects\\rust-practice\\rust\\health-statistics\\tests\\health-statistics.rs","num":10,"id":{"name":"rustc_std_workspace_alloc","disambiguator":[842541340887862638,17591716377464122790]}},{"file_name":"c:\\Users\\Raimi\\Documents\\RustProjects\\rust-practice\\rust\\health-statistics\\tests\\health-statistics.rs","num":11,"id":{"name":"rustc_demangle","disambiguator":[14650435931294811010,18006816567319070280]}},{"file_name":"c:\\Users\\Raimi\\Documents\\RustProjects\\rust-practice\\rust\\health-statistics\\tests\\health-statistics.rs","num":12,"id":{"name":"std_detect","disambiguator":[16073749092757737146,5785406473963590530]}},{"file_name":"c:\\Users\\Raimi\\Documents\\RustProjects\\rust-practice\\rust\\health-statistics\\tests\\health-statistics.rs","num":13,"id":{"name":"panic_unwind","disambiguator":[9426002052484834533,14451905897035318657]}},{"file_name":"c:\\Users\\Raimi\\Documents\\RustProjects\\rust-practice\\rust\\health-statistics\\tests\\health-statistics.rs","num":14,"id":{"name":"health_statistics","disambiguator":[8777838285395589066,138952960248378411]}},{"file_name":"c:\\Users\\Raimi\\Documents\\RustProjects\\rust-practice\\rust\\health-statistics\\tests\\health-statistics.rs","num":15,"id":{"name":"test","disambiguator":[2362059724671402708,10585270743624677136]}},{"file_name":"c:\\Users\\Raimi\\Documents\\RustProjects\\rust-practice\\rust\\health-statistics\\tests\\health-statistics.rs","num":16,"id":{"name":"getopts","disambiguator":[2148500613115993165,6430017358201395089]}},{"file_name":"c:\\Users\\Raimi\\Documents\\RustProjects\\rust-practice\\rust\\health-statistics\\tests\\health-statistics.rs","num":17,"id":{"name":"rustc_std_workspace_std","disambiguator":[17223780013770788073,14494721823926434216]}},{"file_name":"c:\\Users\\Raimi\\Documents\\RustProjects\\rust-practice\\rust\\health-statistics\\tests\\health-statistics.rs","num":18,"id":{"name":"unicode_width","disambiguator":[7203033763437606119,4191258238539543586]}},{"file_name":"c:\\Users\\Raimi\\Documents\\RustProjects\\rust-practice\\rust\\health-statistics\\tests\\health-statistics.rs","num":19,"id":{"name":"term","disambiguator":[13248425952572553216,10500048093320884310]}}],"span":{"file_name":"tests\\health-statistics.rs","byte_start":0,"byte_end":912,"line_start":1,"line_end":43,"column_start":1,"column_end":2}},"imports":[{"kind":"GlobUse","ref_id":null,"span":{"file_name":"tests\\health-statistics.rs","byte_start":23,"byte_end":24,"line_start":1,"line_end":1,"column_start":24,"column_end":25},"alias_span":null,"name":"*","value":"User","parent":{"krate":0,"index":0}}],"defs":[{"kind":"Mod","id":{"krate":0,"index":0},"span":{"file_name":"tests\\health-statistics.rs","byte_start":0,"byte_end":912,"line_start":1,"line_end":43,"column_start":1,"column_end":2},"name":"","qualname":"::","value":"tests\\health-statistics.rs","parent":null,"children":[{"krate":0,"index":1},{"krate":0,"index":2},{"krate":0,"index":3},{"krate":0,"index":4},{"krate":0,"index":5},{"krate":0,"index":6},{"krate":0,"index":7},{"krate":0,"index":8},{"krate":0,"index":10},{"krate":0,"index":11},{"krate":0,"index":12},{"krate":0,"index":14},{"krate":0,"index":15},{"krate":0,"index":16},{"krate":0,"index":18},{"krate":0,"index":19},{"krate":0,"index":20},{"krate":0,"index":22},{"krate":0,"index":23},{"krate":0,"index":24},{"krate":0,"index":26},{"krate":0,"index":27}],"decl_id":null,"docs":"","sig":null,"attributes":[]},{"kind":"Const","id":{"krate":0,"index":4},"span":{"file_name":"tests\\health-statistics.rs","byte_start":33,"byte_end":37,"line_start":3,"line_end":3,"column_start":7,"column_end":11},"name":"NAME","qualname":"::NAME","value":"&str","parent":null,"children":[],"decl_id":null,"docs":"","sig":null,"attributes":[]},{"kind":"Const","id":{"krate":0,"index":5},"span":{"file_name":"tests\\health-statistics.rs","byte_start":64,"byte_end":67,"line_start":4,"line_end":4,"column_start":7,"column_end":10},"name":"AGE","qualname":"::AGE","value":"u32","parent":null,"children":[],"decl_id":null,"docs":"","sig":null,"attributes":[]},{"kind":"Const","id":{"krate":0,"index":6},"span":{"file_name":"tests\\health-statistics.rs","byte_start":85,"byte_end":91,"line_start":5,"line_end":5,"column_start":7,"column_end":13},"name":"WEIGHT","qualname":"::WEIGHT","value":"f32","parent":null,"children":[],"decl_id":null,"docs":"","sig":null,"attributes":[]},{"kind":"Function","id":{"krate":0,"index":10},"span":{"file_name":"tests\\health-statistics.rs","byte_start":118,"byte_end":127,"line_start":8,"line_end":8,"column_start":4,"column_end":13},"name":"test_name","qualname":"::test_name","value":"fn test_name()","parent":null,"children":[],"decl_id":null,"docs":"","sig":null,"attributes":[]},{"kind":"Local","id":{"krate":0,"index":4026531850},"span":{"file_name":"tests\\health-statistics.rs","byte_start":140,"byte_end":144,"line_start":9,"line_end":9,"column_start":9,"column_end":13},"name":"user","qualname":"user$HirId { owner: DefId(0:10 ~ health_statistics[9632]::test_name#1), local_id: 15 }","value":"health_statistics::User","parent":null,"children":[],"decl_id":null,"docs":"","sig":null,"attributes":[]},{"kind":"Function","id":{"krate":0,"index":14},"span":{"file_name":"tests\\health-statistics.rs","byte_start":243,"byte_end":251,"line_start":15,"line_end":15,"column_start":4,"column_end":12},"name":"test_age","qualname":"::test_age","value":"fn test_age()","parent":null,"children":[],"decl_id":null,"docs":"","sig":null,"attributes":[{"value":"ignore","span":{"file_name":"tests\\health-statistics.rs","byte_start":230,"byte_end":239,"line_start":14,"line_end":14,"column_start":1,"column_end":10}}]},{"kind":"Local","id":{"krate":0,"index":4026531854},"span":{"file_name":"tests\\health-statistics.rs","byte_start":264,"byte_end":268,"line_start":16,"line_end":16,"column_start":9,"column_end":13},"name":"user","qualname":"user$HirId { owner: DefId(0:14 ~ health_statistics[9632]::test_age#1), local_id: 15 }","value":"health_statistics::User","parent":null,"children":[],"decl_id":null,"docs":"","sig":null,"attributes":[]},{"kind":"Function","id":{"krate":0,"index":18},"span":{"file_name":"tests\\health-statistics.rs","byte_start":365,"byte_end":376,"line_start":22,"line_end":22,"column_start":4,"column_end":15},"name":"test_weight","qualname":"::test_weight","value":"fn test_weight()","parent":null,"children":[],"decl_id":null,"docs":"","sig":null,"attributes":[{"value":"ignore","span":{"file_name":"tests\\health-statistics.rs","byte_start":352,"byte_end":361,"line_start":21,"line_end":21,"column_start":1,"column_end":10}}]},{"kind":"Local","id":{"krate":0,"index":4026531858},"span":{"file_name":"tests\\health-statistics.rs","byte_start":389,"byte_end":393,"line_start":23,"line_end":23,"column_start":9,"column_end":13},"name":"user","qualname":"user$HirId { owner: DefId(0:18 ~ health_statistics[9632]::test_weight#1), local_id: 15 }","value":"health_statistics::User","parent":null,"children":[],"decl_id":null,"docs":"","sig":null,"attributes":[]},{"kind":"Function","id":{"krate":0,"index":22},"span":{"file_name":"tests\\health-statistics.rs","byte_start":517,"byte_end":529,"line_start":29,"line_end":29,"column_start":4,"column_end":16},"name":"test_set_age","qualname":"::test_set_age","value":"fn test_set_age()","parent":null,"children":[],"decl_id":null,"docs":"","sig":null,"attributes":[{"value":"ignore","span":{"file_name":"tests\\health-statistics.rs","byte_start":504,"byte_end":513,"line_start":28,"line_end":28,"column_start":1,"column_end":10}}]},{"kind":"Local","id":{"krate":0,"index":2684354582},"span":{"file_name":"tests\\health-statistics.rs","byte_start":542,"byte_end":549,"line_start":30,"line_end":30,"column_start":9,"column_end":16},"name":"new_age","qualname":"new_age$HirId { owner: DefId(0:22 ~ health_statistics[9632]::test_set_age#1), local_id: 5 }","value":"u32","parent":null,"children":[],"decl_id":null,"docs":"","sig":null,"attributes":[]},{"kind":"Local","id":{"krate":0,"index":2818572310},"span":{"file_name":"tests\\health-statistics.rs","byte_start":573,"byte_end":577,"line_start":31,"line_end":31,"column_start":13,"column_end":17},"name":"user","qualname":"user$HirId { owner: DefId(0:22 ~ health_statistics[9632]::test_set_age#1), local_id: 21 }","value":"health_statistics::User","parent":null,"children":[],"decl_id":null,"docs":"","sig":null,"attributes":[]},{"kind":"Function","id":{"krate":0,"index":26},"span":{"file_name":"tests\\health-statistics.rs","byte_start":705,"byte_end":720,"line_start":38,"line_end":38,"column_start":4,"column_end":19},"name":"test_set_weight","qualname":"::test_set_weight","value":"fn test_set_weight()","parent":null,"children":[],"decl_id":null,"docs":"","sig":null,"attributes":[{"value":"ignore","span":{"file_name":"tests\\health-statistics.rs","byte_start":692,"byte_end":701,"line_start":37,"line_end":37,"column_start":1,"column_end":10}}]},{"kind":"Local","id":{"krate":0,"index":2684354586},"span":{"file_name":"tests\\health-statistics.rs","byte_start":733,"byte_end":743,"line_start":39,"line_end":39,"column_start":9,"column_end":19},"name":"new_weight","qualname":"new_weight$HirId { owner: DefId(0:26 ~ health_statistics[9632]::test_set_weight#1), local_id: 5 }","value":"f32","parent":null,"children":[],"decl_id":null,"docs":"","sig":null,"attributes":[]},{"kind":"Local","id":{"krate":0,"index":2818572314},"span":{"file_name":"tests\\health-statistics.rs","byte_start":770,"byte_end":774,"line_start":40,"line_end":40,"column_start":13,"column_end":17},"name":"user","qualname":"user$HirId { owner: DefId(0:26 ~ health_statistics[9632]::test_set_weight#1), local_id: 21 }","value":"health_statistics::User","parent":null,"children":[],"decl_id":null,"docs":"","sig":null,"attributes":[]}],"impls":[],"refs":[{"kind":"Mod","span":{"file_name":"tests\\health-statistics.rs","byte_start":4,"byte_end":21,"line_start":1,"line_end":1,"column_start":5,"column_end":22},"ref_id":{"krate":14,"index":0}},{"kind":"Function","span":{"file_name":"tests\\health-statistics.rs","byte_start":153,"byte_end":156,"line_start":9,"line_end":9,"column_start":22,"column_end":25},"ref_id":{"krate":14,"index":8}},{"kind":"Type","span":{"file_name":"tests\\health-statistics.rs","byte_start":147,"byte_end":151,"line_start":9,"line_end":9,"column_start":16,"column_end":20},"ref_id":{"krate":14,"index":3}},{"kind":"Function","span":{"file_name":"tests\\health-statistics.rs","byte_start":162,"byte_end":166,"line_start":9,"line_end":9,"column_start":31,"column_end":35},"ref_id":{"krate":2,"index":2758}},{"kind":"Variable","span":{"file_name":"tests\\health-statistics.rs","byte_start":157,"byte_end":161,"line_start":9,"line_end":9,"column_start":26,"column_end":30},"ref_id":{"krate":0,"index":4}},{"kind":"Variable","span":{"file_name":"tests\\health-statistics.rs","byte_start":170,"byte_end":173,"line_start":9,"line_end":9,"column_start":39,"column_end":42},"ref_id":{"krate":0,"index":5}},{"kind":"Variable","span":{"file_name":"tests\\health-statistics.rs","byte_start":175,"byte_end":181,"line_start":9,"line_end":9,"column_start":44,"column_end":50},"ref_id":{"krate":0,"index":6}},{"kind":"Function","span":{"file_name":"tests\\health-statistics.rs","byte_start":204,"byte_end":208,"line_start":10,"line_end":10,"column_start":21,"column_end":25},"ref_id":{"krate":14,"index":9}},{"kind":"Variable","span":{"file_name":"tests\\health-statistics.rs","byte_start":199,"byte_end":203,"line_start":10,"line_end":10,"column_start":16,"column_end":20},"ref_id":{"krate":0,"index":4026531850}},{"kind":"Variable","span":{"file_name":"tests\\health-statistics.rs","byte_start":212,"byte_end":216,"line_start":10,"line_end":10,"column_start":29,"column_end":33},"ref_id":{"krate":0,"index":4}},{"kind":"Function","span":{"file_name":"tests\\health-statistics.rs","byte_start":277,"byte_end":280,"line_start":16,"line_end":16,"column_start":22,"column_end":25},"ref_id":{"krate":14,"index":8}},{"kind":"Type","span":{"file_name":"tests\\health-statistics.rs","byte_start":271,"byte_end":275,"line_start":16,"line_end":16,"column_start":16,"column_end":20},"ref_id":{"krate":14,"index":3}},{"kind":"Function","span":{"file_name":"tests\\health-statistics.rs","byte_start":286,"byte_end":290,"line_start":16,"line_end":16,"column_start":31,"column_end":35},"ref_id":{"krate":2,"index":2758}},{"kind":"Variable","span":{"file_name":"tests\\health-statistics.rs","byte_start":281,"byte_end":285,"line_start":16,"line_end":16,"column_start":26,"column_end":30},"ref_id":{"krate":0,"index":4}},{"kind":"Variable","span":{"file_name":"tests\\health-statistics.rs","byte_start":294,"byte_end":297,"line_start":16,"line_end":16,"column_start":39,"column_end":42},"ref_id":{"krate":0,"index":5}},{"kind":"Variable","span":{"file_name":"tests\\health-statistics.rs","byte_start":299,"byte_end":305,"line_start":16,"line_end":16,"column_start":44,"column_end":50},"ref_id":{"krate":0,"index":6}},{"kind":"Function","span":{"file_name":"tests\\health-statistics.rs","byte_start":328,"byte_end":331,"line_start":17,"line_end":17,"column_start":21,"column_end":24},"ref_id":{"krate":14,"index":10}},{"kind":"Variable","span":{"file_name":"tests\\health-statistics.rs","byte_start":323,"byte_end":327,"line_start":17,"line_end":17,"column_start":16,"column_end":20},"ref_id":{"krate":0,"index":4026531854}},{"kind":"Variable","span":{"file_name":"tests\\health-statistics.rs","byte_start":335,"byte_end":338,"line_start":17,"line_end":17,"column_start":28,"column_end":31},"ref_id":{"krate":0,"index":5}},{"kind":"Function","span":{"file_name":"tests\\health-statistics.rs","byte_start":402,"byte_end":405,"line_start":23,"line_end":23,"column_start":22,"column_end":25},"ref_id":{"krate":14,"index":8}},{"kind":"Type","span":{"file_name":"tests\\health-statistics.rs","byte_start":396,"byte_end":400,"line_start":23,"line_end":23,"column_start":16,"column_end":20},"ref_id":{"krate":14,"index":3}},{"kind":"Function","span":{"file_name":"tests\\health-statistics.rs","byte_start":411,"byte_end":415,"line_start":23,"line_end":23,"column_start":31,"column_end":35},"ref_id":{"krate":2,"index":2758}},{"kind":"Variable","span":{"file_name":"tests\\health-statistics.rs","byte_start":406,"byte_end":410,"line_start":23,"line_end":23,"column_start":26,"column_end":30},"ref_id":{"krate":0,"index":4}},{"kind":"Variable","span":{"file_name":"tests\\health-statistics.rs","byte_start":419,"byte_end":422,"line_start":23,"line_end":23,"column_start":39,"column_end":42},"ref_id":{"krate":0,"index":5}},{"kind":"Variable","span":{"file_name":"tests\\health-statistics.rs","byte_start":424,"byte_end":430,"line_start":23,"line_end":23,"column_start":44,"column_end":50},"ref_id":{"krate":0,"index":6}},{"kind":"Function","span":{"file_name":"tests\\health-statistics.rs","byte_start":470,"byte_end":473,"line_start":24,"line_end":24,"column_start":38,"column_end":41},"ref_id":{"krate":1,"index":432}},{"kind":"Function","span":{"file_name":"tests\\health-statistics.rs","byte_start":451,"byte_end":457,"line_start":24,"line_end":24,"column_start":19,"column_end":25},"ref_id":{"krate":14,"index":11}},{"kind":"Variable","span":{"file_name":"tests\\health-statistics.rs","byte_start":446,"byte_end":450,"line_start":24,"line_end":24,"column_start":14,"column_end":18},"ref_id":{"krate":0,"index":4026531858}},{"kind":"Variable","span":{"file_name":"tests\\health-statistics.rs","byte_start":462,"byte_end":468,"line_start":24,"line_end":24,"column_start":30,"column_end":36},"ref_id":{"krate":0,"index":6}},{"kind":"Variable","span":{"file_name":"tests\\health-statistics.rs","byte_start":483,"byte_end":490,"line_start":24,"line_end":24,"column_start":51,"column_end":58},"ref_id":{"krate":2,"index":129}},{"kind":"Function","span":{"file_name":"tests\\health-statistics.rs","byte_start":586,"byte_end":589,"line_start":31,"line_end":31,"column_start":26,"column_end":29},"ref_id":{"krate":14,"index":8}},{"kind":"Type","span":{"file_name":"tests\\health-statistics.rs","byte_start":580,"byte_end":584,"line_start":31,"line_end":31,"column_start":20,"column_end":24},"ref_id":{"krate":14,"index":3}},{"kind":"Function","span":{"file_name":"tests\\health-statistics.rs","byte_start":595,"byte_end":599,"line_start":31,"line_end":31,"column_start":35,"column_end":39},"ref_id":{"krate":2,"index":2758}},{"kind":"Variable","span":{"file_name":"tests\\health-statistics.rs","byte_start":590,"byte_end":594,"line_start":31,"line_end":31,"column_start":30,"column_end":34},"ref_id":{"krate":0,"index":4}},{"kind":"Variable","span":{"file_name":"tests\\health-statistics.rs","byte_start":603,"byte_end":606,"line_start":31,"line_end":31,"column_start":43,"column_end":46},"ref_id":{"krate":0,"index":5}},{"kind":"Variable","span":{"file_name":"tests\\health-statistics.rs","byte_start":608,"byte_end":614,"line_start":31,"line_end":31,"column_start":48,"column_end":54},"ref_id":{"krate":0,"index":6}},{"kind":"Function","span":{"file_name":"tests\\health-statistics.rs","byte_start":626,"byte_end":633,"line_start":32,"line_end":32,"column_start":10,"column_end":17},"ref_id":{"krate":14,"index":12}},{"kind":"Variable","span":{"file_name":"tests\\health-statistics.rs","byte_start":621,"byte_end":625,"line_start":32,"line_end":32,"column_start":5,"column_end":9},"ref_id":{"krate":0,"index":2818572310}},{"kind":"Variable","span":{"file_name":"tests\\health-statistics.rs","byte_start":634,"byte_end":641,"line_start":32,"line_end":32,"column_start":18,"column_end":25},"ref_id":{"krate":0,"index":2684354582}},{"kind":"Function","span":{"file_name":"tests\\health-statistics.rs","byte_start":664,"byte_end":667,"line_start":33,"line_end":33,"column_start":21,"column_end":24},"ref_id":{"krate":14,"index":10}},{"kind":"Variable","span":{"file_name":"tests\\health-statistics.rs","byte_start":659,"byte_end":663,"line_start":33,"line_end":33,"column_start":16,"column_end":20},"ref_id":{"krate":0,"index":2818572310}},{"kind":"Variable","span":{"file_name":"tests\\health-statistics.rs","byte_start":671,"byte_end":678,"line_start":33,"line_end":33,"column_start":28,"column_end":35},"ref_id":{"krate":0,"index":2684354582}},{"kind":"Function","span":{"file_name":"tests\\health-statistics.rs","byte_start":783,"byte_end":786,"line_start":40,"line_end":40,"column_start":26,"column_end":29},"ref_id":{"krate":14,"index":8}},{"kind":"Type","span":{"file_name":"tests\\health-statistics.rs","byte_start":777,"byte_end":781,"line_start":40,"line_end":40,"column_start":20,"column_end":24},"ref_id":{"krate":14,"index":3}},{"kind":"Function","span":{"file_name":"tests\\health-statistics.rs","byte_start":792,"byte_end":796,"line_start":40,"line_end":40,"column_start":35,"column_end":39},"ref_id":{"krate":2,"index":2758}},{"kind":"Variable","span":{"file_name":"tests\\health-statistics.rs","byte_start":787,"byte_end":791,"line_start":40,"line_end":40,"column_start":30,"column_end":34},"ref_id":{"krate":0,"index":4}},{"kind":"Variable","span":{"file_name":"tests\\health-statistics.rs","byte_start":800,"byte_end":803,"line_start":40,"line_end":40,"column_start":43,"column_end":46},"ref_id":{"krate":0,"index":5}},{"kind":"Variable","span":{"file_name":"tests\\health-statistics.rs","byte_start":805,"byte_end":811,"line_start":40,"line_end":40,"column_start":48,"column_end":54},"ref_id":{"krate":0,"index":6}},{"kind":"Function","span":{"file_name":"tests\\health-statistics.rs","byte_start":823,"byte_end":833,"line_start":41,"line_end":41,"column_start":10,"column_end":20},"ref_id":{"krate":14,"index":13}},{"kind":"Variable","span":{"file_name":"tests\\health-statistics.rs","byte_start":818,"byte_end":822,"line_start":41,"line_end":41,"column_start":5,"column_end":9},"ref_id":{"krate":0,"index":2818572314}},{"kind":"Variable","span":{"file_name":"tests\\health-statistics.rs","byte_start":834,"byte_end":844,"line_start":41,"line_end":41,"column_start":21,"column_end":31},"ref_id":{"krate":0,"index":2684354586}},{"kind":"Function","span":{"file_name":"tests\\health-statistics.rs","byte_start":888,"byte_end":891,"line_start":42,"line_end":42,"column_start":42,"column_end":45},"ref_id":{"krate":1,"index":432}},{"kind":"Function","span":{"file_name":"tests\\health-statistics.rs","byte_start":865,"byte_end":871,"line_start":42,"line_end":42,"column_start":19,"column_end":25},"ref_id":{"krate":14,"index":11}},{"kind":"Variable","span":{"file_name":"tests\\health-statistics.rs","byte_start":860,"byte_end":864,"line_start":42,"line_end":42,"column_start":14,"column_end":18},"ref_id":{"krate":0,"index":2818572314}},{"kind":"Variable","span":{"file_name":"tests\\health-statistics.rs","byte_start":876,"byte_end":886,"line_start":42,"line_end":42,"column_start":30,"column_end":40},"ref_id":{"krate":0,"index":2684354586}},{"kind":"Variable","span":{"file_name":"tests\\health-statistics.rs","byte_start":901,"byte_end":908,"line_start":42,"line_end":42,"column_start":55,"column_end":62},"ref_id":{"krate":2,"index":129}}],"macro_refs":[],"relations":[]}