{"config":{"output_file":null,"full_docs":false,"pub_only":false,"reachable_only":false,"distro_crate":false,"signatures":false,"borrow_data":false},"version":"0.19.1","compilation":{"directory":"c:\\Users\\Raimi\\Documents\\RustProjects\\rust-practice\\rust\\magazine-cutout","program":"C:\\Users\\Raimi\\.rustup\\toolchains\\stable-x86_64-pc-windows-msvc\\bin\\rls.exe","arguments":[],"output":"c:\\Users\\Raimi\\Documents\\RustProjects\\rust-practice\\rust\\magazine-cutout\\target\\rls\\debug\\deps\\libmagazine_cutout-8fefc98076d92d82.rmeta"},"prelude":{"crate_id":{"name":"magazine_cutout","disambiguator":[2796695335269701926,9447796399862361725]},"crate_root":"src","external_crates":[{"file_name":"c:\\Users\\Raimi\\Documents\\RustProjects\\rust-practice\\rust\\magazine-cutout\\src\\lib.rs","num":1,"id":{"name":"std","disambiguator":[902711862199739234,15082167224296373374]}},{"file_name":"c:\\Users\\Raimi\\Documents\\RustProjects\\rust-practice\\rust\\magazine-cutout\\src\\lib.rs","num":2,"id":{"name":"core","disambiguator":[5048311760381386034,12753961808535803278]}},{"file_name":"c:\\Users\\Raimi\\Documents\\RustProjects\\rust-practice\\rust\\magazine-cutout\\src\\lib.rs","num":3,"id":{"name":"compiler_builtins","disambiguator":[847775214756591688,12437863933651081164]}},{"file_name":"c:\\Users\\Raimi\\Documents\\RustProjects\\rust-practice\\rust\\magazine-cutout\\src\\lib.rs","num":4,"id":{"name":"rustc_std_workspace_core","disambiguator":[18098153966720408130,4102567439342721650]}},{"file_name":"c:\\Users\\Raimi\\Documents\\RustProjects\\rust-practice\\rust\\magazine-cutout\\src\\lib.rs","num":5,"id":{"name":"alloc","disambiguator":[14085577876822856882,15393158987199036233]}},{"file_name":"c:\\Users\\Raimi\\Documents\\RustProjects\\rust-practice\\rust\\magazine-cutout\\src\\lib.rs","num":6,"id":{"name":"libc","disambiguator":[3188366355873518403,14471389999965490426]}},{"file_name":"c:\\Users\\Raimi\\Documents\\RustProjects\\rust-practice\\rust\\magazine-cutout\\src\\lib.rs","num":7,"id":{"name":"unwind","disambiguator":[10237517513868340142,18396708545822173986]}},{"file_name":"c:\\Users\\Raimi\\Documents\\RustProjects\\rust-practice\\rust\\magazine-cutout\\src\\lib.rs","num":8,"id":{"name":"cfg_if","disambiguator":[17305999185247584930,14125623615750666193]}},{"file_name":"c:\\Users\\Raimi\\Documents\\RustProjects\\rust-practice\\rust\\magazine-cutout\\src\\lib.rs","num":9,"id":{"name":"hashbrown","disambiguator":[7451980452763147359,4800032867518142595]}},{"file_name":"c:\\Users\\Raimi\\Documents\\RustProjects\\rust-practice\\rust\\magazine-cutout\\src\\lib.rs","num":10,"id":{"name":"rustc_std_workspace_alloc","disambiguator":[842541340887862638,17591716377464122790]}},{"file_name":"c:\\Users\\Raimi\\Documents\\RustProjects\\rust-practice\\rust\\magazine-cutout\\src\\lib.rs","num":11,"id":{"name":"rustc_demangle","disambiguator":[14650435931294811010,18006816567319070280]}},{"file_name":"c:\\Users\\Raimi\\Documents\\RustProjects\\rust-practice\\rust\\magazine-cutout\\src\\lib.rs","num":12,"id":{"name":"std_detect","disambiguator":[16073749092757737146,5785406473963590530]}},{"file_name":"c:\\Users\\Raimi\\Documents\\RustProjects\\rust-practice\\rust\\magazine-cutout\\src\\lib.rs","num":13,"id":{"name":"panic_unwind","disambiguator":[9426002052484834533,14451905897035318657]}},{"file_name":"c:\\Users\\Raimi\\Documents\\RustProjects\\rust-practice\\rust\\magazine-cutout\\src\\lib.rs","num":14,"id":{"name":"test","disambiguator":[2362059724671402708,10585270743624677136]}},{"file_name":"c:\\Users\\Raimi\\Documents\\RustProjects\\rust-practice\\rust\\magazine-cutout\\src\\lib.rs","num":15,"id":{"name":"getopts","disambiguator":[2148500613115993165,6430017358201395089]}},{"file_name":"c:\\Users\\Raimi\\Documents\\RustProjects\\rust-practice\\rust\\magazine-cutout\\src\\lib.rs","num":16,"id":{"name":"rustc_std_workspace_std","disambiguator":[17223780013770788073,14494721823926434216]}},{"file_name":"c:\\Users\\Raimi\\Documents\\RustProjects\\rust-practice\\rust\\magazine-cutout\\src\\lib.rs","num":17,"id":{"name":"unicode_width","disambiguator":[7203033763437606119,4191258238539543586]}},{"file_name":"c:\\Users\\Raimi\\Documents\\RustProjects\\rust-practice\\rust\\magazine-cutout\\src\\lib.rs","num":18,"id":{"name":"term","disambiguator":[13248425952572553216,10500048093320884310]}}],"span":{"file_name":"src\\lib.rs","byte_start":130,"byte_end":823,"line_start":3,"line_end":28,"column_start":1,"column_end":2}},"imports":[{"kind":"Use","ref_id":{"krate":1,"index":1396},"span":{"file_name":"src\\lib.rs","byte_start":189,"byte_end":197,"line_start":5,"line_end":5,"column_start":41,"column_end":49},"alias_span":null,"name":"Occupied","value":"","parent":{"krate":0,"index":0}},{"kind":"Use","ref_id":{"krate":1,"index":1397},"span":{"file_name":"src\\lib.rs","byte_start":189,"byte_end":197,"line_start":5,"line_end":5,"column_start":41,"column_end":49},"alias_span":null,"name":"Occupied","value":"","parent":{"krate":0,"index":0}},{"kind":"Use","ref_id":{"krate":1,"index":1399},"span":{"file_name":"src\\lib.rs","byte_start":199,"byte_end":205,"line_start":5,"line_end":5,"column_start":51,"column_end":57},"alias_span":null,"name":"Vacant","value":"","parent":{"krate":0,"index":0}},{"kind":"Use","ref_id":{"krate":1,"index":1400},"span":{"file_name":"src\\lib.rs","byte_start":199,"byte_end":205,"line_start":5,"line_end":5,"column_start":51,"column_end":57},"alias_span":null,"name":"Vacant","value":"","parent":{"krate":0,"index":0}},{"kind":"Use","ref_id":{"krate":1,"index":1406},"span":{"file_name":"src\\lib.rs","byte_start":240,"byte_end":253,"line_start":6,"line_end":6,"column_start":33,"column_end":46},"alias_span":null,"name":"OccupiedEntry","value":"","parent":{"krate":0,"index":0}},{"kind":"Use","ref_id":{"krate":1,"index":1092},"span":{"file_name":"src\\lib.rs","byte_start":277,"byte_end":284,"line_start":7,"line_end":7,"column_start":23,"column_end":30},"alias_span":null,"name":"HashMap","value":"","parent":{"krate":0,"index":0}}],"defs":[{"kind":"Mod","id":{"krate":0,"index":0},"span":{"file_name":"src\\lib.rs","byte_start":130,"byte_end":823,"line_start":3,"line_end":28,"column_start":1,"column_end":2},"name":"","qualname":"::","value":"src\\lib.rs","parent":null,"children":[{"krate":0,"index":1},{"krate":0,"index":2},{"krate":0,"index":3},{"krate":0,"index":4},{"krate":0,"index":5},{"krate":0,"index":7},{"krate":0,"index":8},{"krate":0,"index":10},{"krate":0,"index":13},{"krate":0,"index":16},{"krate":0,"index":17}],"decl_id":null,"docs":"","sig":null,"attributes":[{"value":"allow(unused)","span":{"file_name":"src\\lib.rs","byte_start":130,"byte_end":147,"line_start":3,"line_end":3,"column_start":1,"column_end":18}}]},{"kind":"Local","id":{"krate":0,"index":1073741840},"span":{"file_name":"src\\lib.rs","byte_start":313,"byte_end":321,"line_start":9,"line_end":9,"column_start":27,"column_end":35},"name":"magazine","qualname":"::can_construct_note::magazine","value":"&[&str]","parent":null,"children":[],"decl_id":null,"docs":"","sig":null,"attributes":[]},{"kind":"Local","id":{"krate":0,"index":536870928},"span":{"file_name":"src\\lib.rs","byte_start":332,"byte_end":336,"line_start":9,"line_end":9,"column_start":46,"column_end":50},"name":"note","qualname":"::can_construct_note::note","value":"&[&str]","parent":null,"children":[],"decl_id":null,"docs":"","sig":null,"attributes":[]},{"kind":"Function","id":{"krate":0,"index":16},"span":{"file_name":"src\\lib.rs","byte_start":294,"byte_end":312,"line_start":9,"line_end":9,"column_start":8,"column_end":26},"name":"can_construct_note","qualname":"::can_construct_note","value":"pub fn can_construct_note(&[&str], &[&str]) -> bool","parent":null,"children":[],"decl_id":null,"docs":"","sig":null,"attributes":[]},{"kind":"Local","id":{"krate":0,"index":3355443216},"span":{"file_name":"src\\lib.rs","byte_start":369,"byte_end":372,"line_start":10,"line_end":10,"column_start":13,"column_end":16},"name":"map","qualname":"map$HirId { owner: DefId(0:16 ~ magazine_cutout[26cf]::can_construct_note), local_id: 19 }","value":"std::collections::HashMap<&str, u32>","parent":null,"children":[],"decl_id":null,"docs":"","sig":null,"attributes":[]},{"kind":"Local","id":{"krate":0,"index":3288334352},"span":{"file_name":"src\\lib.rs","byte_start":428,"byte_end":436,"line_start":12,"line_end":12,"column_start":17,"column_end":25},"name":"iter","qualname":"iter$HirId { owner: DefId(0:16 ~ magazine_cutout[26cf]::can_construct_note), local_id: 35 }","value":"std::slice::Iter<&str>","parent":null,"children":[],"decl_id":null,"docs":"","sig":null,"attributes":[]},{"kind":"Local","id":{"krate":0,"index":3892314128},"span":{"file_name":"src\\lib.rs","byte_start":428,"byte_end":436,"line_start":12,"line_end":12,"column_start":17,"column_end":25},"name":"__next","qualname":"__next$HirId { owner: DefId(0:16 ~ magazine_cutout[26cf]::can_construct_note), local_id: 23 }","value":"&&str","parent":null,"children":[],"decl_id":null,"docs":"","sig":null,"attributes":[]},{"kind":"Local","id":{"krate":0,"index":402653200},"span":{"file_name":"src\\lib.rs","byte_start":420,"byte_end":424,"line_start":12,"line_end":12,"column_start":9,"column_end":13},"name":"val","qualname":"val$HirId { owner: DefId(0:16 ~ magazine_cutout[26cf]::can_construct_note), local_id: 24 }","value":"&&str","parent":null,"children":[],"decl_id":null,"docs":"","sig":null,"attributes":[]},{"kind":"Local","id":{"krate":0,"index":3019898896},"span":{"file_name":"src\\lib.rs","byte_start":420,"byte_end":424,"line_start":12,"line_end":12,"column_start":9,"column_end":13},"name":"word","qualname":"word$HirId { owner: DefId(0:16 ~ magazine_cutout[26cf]::can_construct_note), local_id: 45 }","value":"&&str","parent":null,"children":[],"decl_id":null,"docs":"","sig":null,"attributes":[]},{"kind":"Local","id":{"krate":0,"index":2852126736},"span":{"file_name":"src\\lib.rs","byte_start":505,"byte_end":509,"line_start":15,"line_end":15,"column_start":17,"column_end":21},"name":"iter","qualname":"iter$HirId { owner: DefId(0:16 ~ magazine_cutout[26cf]::can_construct_note), local_id: 85 }","value":"std::slice::Iter<&str>","parent":null,"children":[],"decl_id":null,"docs":"","sig":null,"attributes":[]},{"kind":"Local","id":{"krate":0,"index":2449473552},"span":{"file_name":"src\\lib.rs","byte_start":505,"byte_end":509,"line_start":15,"line_end":15,"column_start":17,"column_end":21},"name":"__next","qualname":"__next$HirId { owner: DefId(0:16 ~ magazine_cutout[26cf]::can_construct_note), local_id: 73 }","value":"&&str","parent":null,"children":[],"decl_id":null,"docs":"","sig":null,"attributes":[]},{"kind":"Local","id":{"krate":0,"index":1375731728},"span":{"file_name":"src\\lib.rs","byte_start":497,"byte_end":501,"line_start":15,"line_end":15,"column_start":9,"column_end":13},"name":"val","qualname":"val$HirId { owner: DefId(0:16 ~ magazine_cutout[26cf]::can_construct_note), local_id: 74 }","value":"&&str","parent":null,"children":[],"decl_id":null,"docs":"","sig":null,"attributes":[]},{"kind":"Local","id":{"krate":0,"index":4194304016},"span":{"file_name":"src\\lib.rs","byte_start":497,"byte_end":501,"line_start":15,"line_end":15,"column_start":9,"column_end":13},"name":"word","qualname":"word$HirId { owner: DefId(0:16 ~ magazine_cutout[26cf]::can_construct_note), local_id: 95 }","value":"&&str","parent":null,"children":[],"decl_id":null,"docs":"","sig":null,"attributes":[]},{"kind":"Local","id":{"krate":0,"index":2516582416},"span":{"file_name":"src\\lib.rs","byte_start":565,"byte_end":570,"line_start":17,"line_end":17,"column_start":22,"column_end":27},"name":"entry","qualname":"entry$HirId { owner: DefId(0:16 ~ magazine_cutout[26cf]::can_construct_note), local_id: 105 }","value":"std::collections::hash_map::OccupiedEntry<&str, u32>","parent":null,"children":[],"decl_id":null,"docs":"","sig":null,"attributes":[]}],"impls":[],"refs":[{"kind":"Type","span":{"file_name":"src\\lib.rs","byte_start":153,"byte_end":156,"line_start":5,"line_end":5,"column_start":5,"column_end":8},"ref_id":{"krate":1,"index":1396}},{"kind":"Type","span":{"file_name":"src\\lib.rs","byte_start":158,"byte_end":169,"line_start":5,"line_end":5,"column_start":10,"column_end":21},"ref_id":{"krate":1,"index":1396}},{"kind":"Type","span":{"file_name":"src\\lib.rs","byte_start":171,"byte_end":179,"line_start":5,"line_end":5,"column_start":23,"column_end":31},"ref_id":{"krate":1,"index":1396}},{"kind":"Type","span":{"file_name":"src\\lib.rs","byte_start":181,"byte_end":186,"line_start":5,"line_end":5,"column_start":33,"column_end":38},"ref_id":{"krate":1,"index":1396}},{"kind":"Type","span":{"file_name":"src\\lib.rs","byte_start":153,"byte_end":156,"line_start":5,"line_end":5,"column_start":5,"column_end":8},"ref_id":{"krate":1,"index":1396}},{"kind":"Type","span":{"file_name":"src\\lib.rs","byte_start":158,"byte_end":169,"line_start":5,"line_end":5,"column_start":10,"column_end":21},"ref_id":{"krate":1,"index":1396}},{"kind":"Type","span":{"file_name":"src\\lib.rs","byte_start":171,"byte_end":179,"line_start":5,"line_end":5,"column_start":23,"column_end":31},"ref_id":{"krate":1,"index":1396}},{"kind":"Type","span":{"file_name":"src\\lib.rs","byte_start":181,"byte_end":186,"line_start":5,"line_end":5,"column_start":33,"column_end":38},"ref_id":{"krate":1,"index":1396}},{"kind":"Type","span":{"file_name":"src\\lib.rs","byte_start":153,"byte_end":156,"line_start":5,"line_end":5,"column_start":5,"column_end":8},"ref_id":{"krate":1,"index":1399}},{"kind":"Type","span":{"file_name":"src\\lib.rs","byte_start":158,"byte_end":169,"line_start":5,"line_end":5,"column_start":10,"column_end":21},"ref_id":{"krate":1,"index":1399}},{"kind":"Type","span":{"file_name":"src\\lib.rs","byte_start":171,"byte_end":179,"line_start":5,"line_end":5,"column_start":23,"column_end":31},"ref_id":{"krate":1,"index":1399}},{"kind":"Type","span":{"file_name":"src\\lib.rs","byte_start":181,"byte_end":186,"line_start":5,"line_end":5,"column_start":33,"column_end":38},"ref_id":{"krate":1,"index":1399}},{"kind":"Type","span":{"file_name":"src\\lib.rs","byte_start":153,"byte_end":156,"line_start":5,"line_end":5,"column_start":5,"column_end":8},"ref_id":{"krate":1,"index":1399}},{"kind":"Type","span":{"file_name":"src\\lib.rs","byte_start":158,"byte_end":169,"line_start":5,"line_end":5,"column_start":10,"column_end":21},"ref_id":{"krate":1,"index":1399}},{"kind":"Type","span":{"file_name":"src\\lib.rs","byte_start":171,"byte_end":179,"line_start":5,"line_end":5,"column_start":23,"column_end":31},"ref_id":{"krate":1,"index":1399}},{"kind":"Type","span":{"file_name":"src\\lib.rs","byte_start":181,"byte_end":186,"line_start":5,"line_end":5,"column_start":33,"column_end":38},"ref_id":{"krate":1,"index":1399}},{"kind":"Mod","span":{"file_name":"src\\lib.rs","byte_start":212,"byte_end":215,"line_start":6,"line_end":6,"column_start":5,"column_end":8},"ref_id":{"krate":1,"index":0}},{"kind":"Mod","span":{"file_name":"src\\lib.rs","byte_start":217,"byte_end":228,"line_start":6,"line_end":6,"column_start":10,"column_end":21},"ref_id":{"krate":1,"index":997}},{"kind":"Mod","span":{"file_name":"src\\lib.rs","byte_start":230,"byte_end":238,"line_start":6,"line_end":6,"column_start":23,"column_end":31},"ref_id":{"krate":1,"index":2127}},{"kind":"Mod","span":{"file_name":"src\\lib.rs","byte_start":259,"byte_end":262,"line_start":7,"line_end":7,"column_start":5,"column_end":8},"ref_id":{"krate":1,"index":0}},{"kind":"Mod","span":{"file_name":"src\\lib.rs","byte_start":264,"byte_end":275,"line_start":7,"line_end":7,"column_start":10,"column_end":21},"ref_id":{"krate":1,"index":997}},{"kind":"Type","span":{"file_name":"src\\lib.rs","byte_start":374,"byte_end":381,"line_start":10,"line_end":10,"column_start":18,"column_end":25},"ref_id":{"krate":1,"index":1092}},{"kind":"Function","span":{"file_name":"src\\lib.rs","byte_start":404,"byte_end":407,"line_start":10,"line_end":10,"column_start":48,"column_end":51},"ref_id":{"krate":1,"index":1100}},{"kind":"Type","span":{"file_name":"src\\lib.rs","byte_start":395,"byte_end":402,"line_start":10,"line_end":10,"column_start":39,"column_end":46},"ref_id":{"krate":1,"index":1092}},{"kind":"Variable","span":{"file_name":"src\\lib.rs","byte_start":428,"byte_end":436,"line_start":12,"line_end":12,"column_start":17,"column_end":25},"ref_id":{"krate":0,"index":1073741840}},{"kind":"Variable","span":{"file_name":"src\\lib.rs","byte_start":420,"byte_end":424,"line_start":12,"line_end":12,"column_start":9,"column_end":13},"ref_id":{"krate":2,"index":39950}},{"kind":"Function","span":{"file_name":"src\\lib.rs","byte_start":464,"byte_end":473,"line_start":13,"line_end":13,"column_start":26,"column_end":35},"ref_id":{"krate":1,"index":1638}},{"kind":"Function","span":{"file_name":"src\\lib.rs","byte_start":452,"byte_end":457,"line_start":13,"line_end":13,"column_start":14,"column_end":19},"ref_id":{"krate":1,"index":1129}},{"kind":"Variable","span":{"file_name":"src\\lib.rs","byte_start":448,"byte_end":451,"line_start":13,"line_end":13,"column_start":10,"column_end":13},"ref_id":{"krate":0,"index":3355443216}},{"kind":"Variable","span":{"file_name":"src\\lib.rs","byte_start":458,"byte_end":462,"line_start":13,"line_end":13,"column_start":20,"column_end":24},"ref_id":{"krate":0,"index":3019898896}},{"kind":"Variable","span":{"file_name":"src\\lib.rs","byte_start":505,"byte_end":509,"line_start":15,"line_end":15,"column_start":17,"column_end":21},"ref_id":{"krate":0,"index":536870928}},{"kind":"Variable","span":{"file_name":"src\\lib.rs","byte_start":497,"byte_end":501,"line_start":15,"line_end":15,"column_start":9,"column_end":13},"ref_id":{"krate":2,"index":39950}},{"kind":"Function","span":{"file_name":"src\\lib.rs","byte_start":530,"byte_end":535,"line_start":16,"line_end":16,"column_start":19,"column_end":24},"ref_id":{"krate":1,"index":1129}},{"kind":"Variable","span":{"file_name":"src\\lib.rs","byte_start":526,"byte_end":529,"line_start":16,"line_end":16,"column_start":15,"column_end":18},"ref_id":{"krate":0,"index":3355443216}},{"kind":"Variable","span":{"file_name":"src\\lib.rs","byte_start":536,"byte_end":540,"line_start":16,"line_end":16,"column_start":25,"column_end":29},"ref_id":{"krate":0,"index":4194304016}},{"kind":"Type","span":{"file_name":"src\\lib.rs","byte_start":556,"byte_end":564,"line_start":17,"line_end":17,"column_start":13,"column_end":21},"ref_id":{"krate":1,"index":1396}},{"kind":"Type","span":{"file_name":"src\\lib.rs","byte_start":556,"byte_end":564,"line_start":17,"line_end":17,"column_start":13,"column_end":21},"ref_id":{"krate":1,"index":1396}},{"kind":"Function","span":{"file_name":"src\\lib.rs","byte_start":603,"byte_end":606,"line_start":18,"line_end":18,"column_start":27,"column_end":30},"ref_id":{"krate":1,"index":1658}},{"kind":"Variable","span":{"file_name":"src\\lib.rs","byte_start":597,"byte_end":602,"line_start":18,"line_end":18,"column_start":21,"column_end":26},"ref_id":{"krate":0,"index":2516582416}},{"kind":"Function","span":{"file_name":"src\\lib.rs","byte_start":642,"byte_end":650,"line_start":19,"line_end":19,"column_start":28,"column_end":36},"ref_id":{"krate":1,"index":1660}},{"kind":"Variable","span":{"file_name":"src\\lib.rs","byte_start":636,"byte_end":641,"line_start":19,"line_end":19,"column_start":22,"column_end":27},"ref_id":{"krate":0,"index":2516582416}},{"kind":"Type","span":{"file_name":"src\\lib.rs","byte_start":762,"byte_end":768,"line_start":24,"line_end":24,"column_start":13,"column_end":19},"ref_id":{"krate":1,"index":1399}},{"kind":"Type","span":{"file_name":"src\\lib.rs","byte_start":762,"byte_end":768,"line_start":24,"line_end":24,"column_start":13,"column_end":19},"ref_id":{"krate":1,"index":1399}}],"macro_refs":[],"relations":[]}